desdeo_problem/__init__.py
desdeo_problem/problem/Constraint.py
desdeo_problem/problem/Objective.py
desdeo_problem/problem/Problem.py
desdeo_problem/problem/Variable.py
desdeo_problem/problem/__init__.py
desdeo_problem/surrogatemodels/SurrogateModels.py
desdeo_problem/surrogatemodels/__init__.py
desdeo_problem/surrogatemodels/lipschitzian.py
desdeo_problem/testproblems/CarSideImpact.py
desdeo_problem/testproblems/DBMOPP/DBMOPP_generator.py
desdeo_problem/testproblems/DBMOPP/README.md
desdeo_problem/testproblems/DBMOPP/Region.py
desdeo_problem/testproblems/DBMOPP/__init__.py
desdeo_problem/testproblems/DBMOPP/utilities.py
desdeo_problem/testproblems/DummyProblem.py
desdeo_problem/testproblems/EngineeringRealWorld.py
desdeo_problem/testproblems/GAA.py
desdeo_problem/testproblems/MultipleClutchBrakes.py
desdeo_problem/testproblems/RiverPollution.py
desdeo_problem/testproblems/TestProblems.py
desdeo_problem/testproblems/VehicleCrashworthiness.py
desdeo_problem/testproblems/__init__.py
desdeo_problem-1.6.1.dist-info/LICENSE
desdeo_problem-1.6.1.dist-info/METADATA
desdeo_problem-1.6.1.dist-info/WHEEL
desdeo_problem-1.6.1.dist-info/RECORD
